wlc_tools/__init__.py
wlc_tools/diff.py
wlc_tools/rename.py
wlc_tools-0.1.0a0.dist-info/LICENSE
wlc_tools-0.1.0a0.dist-info/METADATA
wlc_tools-0.1.0a0.dist-info/WHEEL
wlc_tools-0.1.0a0.dist-info/top_level.txt
wlc_tools-0.1.0a0.dist-info/RECORD
