Metadata-Version: 2.1
Name: wlc-tools
Version: 0.1.0a0
Summary: deep learning tools for wlc analysis
Home-page: 
Author: wlc
Author-email: lichun_wang1993@163.com
License: MIT
Platform: UNKNOWN
Classifier: License :: OSI Approved :: MIT License
Classifier: Programming Language :: Python
Classifier: Programming Language :: Python :: 3
Classifier: Programming Language :: Python :: 3.6
Classifier: Programming Language :: Python :: Implementation :: CPython
Classifier: Programming Language :: Python :: Implementation :: PyPy
Requires-Python: >=3.6,<=3.11
License-File: LICENSE
Requires-Dist: gpustat (==0.6.0)
Requires-Dist: opencv-python-headless
